csv_shuffler/__init__.py
csv_shuffler/csv_shuffler.py
csv_shuffler-0.0.4.dist-info/LICENSE
csv_shuffler-0.0.4.dist-info/METADATA
csv_shuffler-0.0.4.dist-info/WHEEL
csv_shuffler-0.0.4.dist-info/top_level.txt
csv_shuffler-0.0.4.dist-info/RECORD
