Metadata-Version: 2.1
Name: csv-shuffler
Version: 0.0.4
Summary: A tool to automatically Shuffle lines in a csv file
Home-page: https://github.com/Wittline/csv-shuffler
Author: Ramses Alexander Coraspe Valdez
Author-email: contacto@wittline.com
Classifier: Programming Language :: Python :: 3
Classifier: License :: OSI Approved :: MIT License
Classifier: Operating System :: OS Independent
Requires-Python: >=3.7
License-File: LICENSE
